{
  "build": {
    "preview": {
      "android": {
        "buildType": "apk"
      },
      "env": {
        "EXPO_PUBLIC_API_URL": "https://money-tracking-app-2e4137f53688.herokuapp.com"
      }
    },
    "preview2": {
      "android": {
        "gradleCommand": ":app:assembleRelease"
      }
    },
    "preview3": {
      "developmentClient": true
    },
    "preview4": {
      "distribution": "internal"
    },
    "production": {
      "env": {
        "EXPO_PUBLIC_API_URL": "https://money-tracking-app-2e4137f53688.herokuapp.com"
      },
      "node": "20.12.0"
    }
  }
}
